{"nodes": [{"id": "i_github_oferty_pv_kilo_worktrees_political_celestite_well_configurator_backend_test_order_os2_py", "label": "test_order_os2.py", "file_type": "code", "source_file": "I:\\GitHub\\Oferty_PV\\.kilo\\worktrees\\political-celestite\\well_configurator_backend\\test_order_os2.py", "source_location": "L1"}, {"id": "well_configurator_backend_test_order_os2_db_to_available", "label": "db_to_available()", "file_type": "code", "source_file": "I:\\GitHub\\Oferty_PV\\.kilo\\worktrees\\political-celestite\\well_configurator_backend\\test_order_os2.py", "source_location": "L25"}, {"id": "well_configurator_backend_test_order_os2_test_well", "label": "test_well()", "file_type": "code", "source_file": "I:\\GitHub\\Oferty_PV\\.kilo\\worktrees\\political-celestite\\well_configurator_backend\\test_order_os2.py", "source_location": "L44"}, {"id": "well_configurator_backend_test_order_os2_rationale_1", "label": "Test konfiguracji studni z zam\u00f3wienia OS/000002/AD/2026. Symuluje problematyczn", "file_type": "rationale", "source_file": "I:\\GitHub\\Oferty_PV\\.kilo\\worktrees\\political-celestite\\well_configurator_backend\\test_order_os2.py", "source_location": "L1"}, {"id": "well_configurator_backend_test_order_os2_rationale_45", "label": "Testuje konfiguracj\u0119 studni i wy\u015bwietla wynik.", "file_type": "rationale", "source_file": "I:\\GitHub\\Oferty_PV\\.kilo\\worktrees\\political-celestite\\well_configurator_backend\\test_order_os2.py", "source_location": "L45"}], "edges": [{"source": "i_github_oferty_pv_kilo_worktrees_political_celestite_well_configurator_backend_test_order_os2_py", "target": "sys", "relation": "imports", "context": "import", "confidence": "EXTRACTED", "source_file": "I:\\GitHub\\Oferty_PV\\.kilo\\worktrees\\political-celestite\\well_configurator_backend\\test_order_os2.py", "source_location": "L5", "weight": 1.0}, {"source": "i_github_oferty_pv_kilo_worktrees_political_celestite_well_configurator_backend_test_order_os2_py", "target": "io", "relation": "imports", "context": "import", "confidence": "EXTRACTED", "source_file": "I:\\GitHub\\Oferty_PV\\.kilo\\worktrees\\political-celestite\\well_configurator_backend\\test_order_os2.py", "source_location": "L5", "weight": 1.0}, {"source": "i_github_oferty_pv_kilo_worktrees_political_celestite_well_configurator_backend_test_order_os2_py", "target": "configuration_generator_generator", "relation": "imports_from", "context": "import", "confidence": "EXTRACTED", "source_file": "I:\\GitHub\\Oferty_PV\\.kilo\\worktrees\\political-celestite\\well_configurator_backend\\test_order_os2.py", "source_location": "L9", "weight": 1.0}, {"source": "i_github_oferty_pv_kilo_worktrees_political_celestite_well_configurator_backend_test_order_os2_py", "target": "api_schemas", "relation": "imports_from", "context": "import", "confidence": "EXTRACTED", "source_file": "I:\\GitHub\\Oferty_PV\\.kilo\\worktrees\\political-celestite\\well_configurator_backend\\test_order_os2.py", "source_location": "L10", "weight": 1.0}, {"source": "i_github_oferty_pv_kilo_worktrees_political_celestite_well_configurator_backend_test_order_os2_py", "target": "database_tables", "relation": "imports_from", "context": "import", "confidence": "EXTRACTED", "source_file": "I:\\GitHub\\Oferty_PV\\.kilo\\worktrees\\political-celestite\\well_configurator_backend\\test_order_os2.py", "source_location": "L11", "weight": 1.0}, {"source": "i_github_oferty_pv_kilo_worktrees_political_celestite_well_configurator_backend_test_order_os2_py", "target": "database_local_db", "relation": "imports_from", "context": "import", "confidence": "EXTRACTED", "source_file": "I:\\GitHub\\Oferty_PV\\.kilo\\worktrees\\political-celestite\\well_configurator_backend\\test_order_os2.py", "source_location": "L12", "weight": 1.0}, {"source": "i_github_oferty_pv_kilo_worktrees_political_celestite_well_configurator_backend_test_order_os2_py", "target": "logging", "relation": "imports", "context": "import", "confidence": "EXTRACTED", "source_file": "I:\\GitHub\\Oferty_PV\\.kilo\\worktrees\\political-celestite\\well_configurator_backend\\test_order_os2.py", "source_location": "L13", "weight": 1.0}, {"source": "i_github_oferty_pv_kilo_worktrees_political_celestite_well_configurator_backend_test_order_os2_py", "target": "sqlalchemy_orm", "relation": "imports_from", "context": "import", "confidence": "EXTRACTED", "source_file": "I:\\GitHub\\Oferty_PV\\.kilo\\worktrees\\political-celestite\\well_configurator_backend\\test_order_os2.py", "source_location": "L19", "weight": 1.0}, {"source": "i_github_oferty_pv_kilo_worktrees_political_celestite_well_configurator_backend_test_order_os2_py", "target": "well_configurator_backend_test_order_os2_db_to_available", "relation": "contains", "confidence": "EXTRACTED", "source_file": "I:\\GitHub\\Oferty_PV\\.kilo\\worktrees\\political-celestite\\well_configurator_backend\\test_order_os2.py", "source_location": "L25", "weight": 1.0}, {"source": "i_github_oferty_pv_kilo_worktrees_political_celestite_well_configurator_backend_test_order_os2_py", "target": "well_configurator_backend_test_order_os2_test_well", "relation": "contains", "confidence": "EXTRACTED", "source_file": "I:\\GitHub\\Oferty_PV\\.kilo\\worktrees\\political-celestite\\well_configurator_backend\\test_order_os2.py", "source_location": "L44", "weight": 1.0}, {"source": "well_configurator_backend_test_order_os2_rationale_1", "target": "i_github_oferty_pv_kilo_worktrees_political_celestite_well_configurator_backend_test_order_os2_py", "relation": "rationale_for", "confidence": "EXTRACTED", "source_file": "I:\\GitHub\\Oferty_PV\\.kilo\\worktrees\\political-celestite\\well_configurator_backend\\test_order_os2.py", "source_location": "L1", "weight": 1.0}, {"source": "well_configurator_backend_test_order_os2_rationale_45", "target": "well_configurator_backend_test_order_os2_test_well", "relation": "rationale_for", "confidence": "EXTRACTED", "source_file": "I:\\GitHub\\Oferty_PV\\.kilo\\worktrees\\political-celestite\\well_configurator_backend\\test_order_os2.py", "source_location": "L45", "weight": 1.0}], "raw_calls": [{"caller_nid": "well_configurator_backend_test_order_os2_db_to_available", "callee": "AvailableProduct", "is_member_call": false, "source_file": "I:\\GitHub\\Oferty_PV\\.kilo\\worktrees\\political-celestite\\well_configurator_backend\\test_order_os2.py", "source_location": "L26"}, {"caller_nid": "well_configurator_backend_test_order_os2_test_well", "callee": "print", "is_member_call": false, "source_file": "I:\\GitHub\\Oferty_PV\\.kilo\\worktrees\\political-celestite\\well_configurator_backend\\test_order_os2.py", "source_location": "L46"}, {"caller_nid": "well_configurator_backend_test_order_os2_test_well", "callee": "print", "is_member_call": false, "source_file": "I:\\GitHub\\Oferty_PV\\.kilo\\worktrees\\political-celestite\\well_configurator_backend\\test_order_os2.py", "source_location": "L47"}, {"caller_nid": "well_configurator_backend_test_order_os2_test_well", "callee": "print", "is_member_call": false, "source_file": "I:\\GitHub\\Oferty_PV\\.kilo\\worktrees\\political-celestite\\well_configurator_backend\\test_order_os2.py", "source_location": "L48"}, {"caller_nid": "well_configurator_backend_test_order_os2_test_well", "callee": "print", "is_member_call": false, "source_file": "I:\\GitHub\\Oferty_PV\\.kilo\\worktrees\\political-celestite\\well_configurator_backend\\test_order_os2.py", "source_location": "L51"}, {"caller_nid": "well_configurator_backend_test_order_os2_test_well", "callee": "print", "is_member_call": false, "source_file": "I:\\GitHub\\Oferty_PV\\.kilo\\worktrees\\political-celestite\\well_configurator_backend\\test_order_os2.py", "source_location": "L52"}, {"caller_nid": "well_configurator_backend_test_order_os2_test_well", "callee": "print", "is_member_call": false, "source_file": "I:\\GitHub\\Oferty_PV\\.kilo\\worktrees\\political-celestite\\well_configurator_backend\\test_order_os2.py", "source_location": "L53"}, {"caller_nid": "well_configurator_backend_test_order_os2_test_well", "callee": "WellConfigInput", "is_member_call": false, "source_file": "I:\\GitHub\\Oferty_PV\\.kilo\\worktrees\\political-celestite\\well_configurator_backend\\test_order_os2.py", "source_location": "L55"}, {"caller_nid": "well_configurator_backend_test_order_os2_test_well", "callee": "ProductModel", "is_member_call": false, "source_file": "I:\\GitHub\\Oferty_PV\\.kilo\\worktrees\\political-celestite\\well_configurator_backend\\test_order_os2.py", "source_location": "L68"}, {"caller_nid": "well_configurator_backend_test_order_os2_test_well", "callee": "append", "is_member_call": true, "source_file": "I:\\GitHub\\Oferty_PV\\.kilo\\worktrees\\political-celestite\\well_configurator_backend\\test_order_os2.py", "source_location": "L77"}, {"caller_nid": "well_configurator_backend_test_order_os2_test_well", "callee": "ConfigurationGenerator", "is_member_call": false, "source_file": "I:\\GitHub\\Oferty_PV\\.kilo\\worktrees\\political-celestite\\well_configurator_backend\\test_order_os2.py", "source_location": "L79"}, {"caller_nid": "well_configurator_backend_test_order_os2_test_well", "callee": "generate", "is_member_call": true, "source_file": "I:\\GitHub\\Oferty_PV\\.kilo\\worktrees\\political-celestite\\well_configurator_backend\\test_order_os2.py", "source_location": "L80"}, {"caller_nid": "well_configurator_backend_test_order_os2_test_well", "callee": "print", "is_member_call": false, "source_file": "I:\\GitHub\\Oferty_PV\\.kilo\\worktrees\\political-celestite\\well_configurator_backend\\test_order_os2.py", "source_location": "L84"}, {"caller_nid": "well_configurator_backend_test_order_os2_test_well", "callee": "print", "is_member_call": false, "source_file": "I:\\GitHub\\Oferty_PV\\.kilo\\worktrees\\political-celestite\\well_configurator_backend\\test_order_os2.py", "source_location": "L86"}, {"caller_nid": "well_configurator_backend_test_order_os2_test_well", "callee": "len", "is_member_call": false, "source_file": "I:\\GitHub\\Oferty_PV\\.kilo\\worktrees\\political-celestite\\well_configurator_backend\\test_order_os2.py", "source_location": "L86"}, {"caller_nid": "well_configurator_backend_test_order_os2_test_well", "callee": "print", "is_member_call": false, "source_file": "I:\\GitHub\\Oferty_PV\\.kilo\\worktrees\\political-celestite\\well_configurator_backend\\test_order_os2.py", "source_location": "L89"}, {"caller_nid": "well_configurator_backend_test_order_os2_test_well", "callee": "print", "is_member_call": false, "source_file": "I:\\GitHub\\Oferty_PV\\.kilo\\worktrees\\political-celestite\\well_configurator_backend\\test_order_os2.py", "source_location": "L91"}, {"caller_nid": "well_configurator_backend_test_order_os2_test_well", "callee": "print", "is_member_call": false, "source_file": "I:\\GitHub\\Oferty_PV\\.kilo\\worktrees\\political-celestite\\well_configurator_backend\\test_order_os2.py", "source_location": "L93"}]}