{"nodes": [{"id": "i_github_oferty_pv_kilo_worktrees_iced_dreadnought_agent_rules_cpp_coding_style_md", "label": "cpp-coding-style.md", "file_type": "document", "source_file": "I:\\GitHub\\Oferty_PV\\.kilo\\worktrees\\iced-dreadnought\\.agent\\rules\\cpp-coding-style.md", "source_location": "L1"}, {"id": "rules_cpp_coding_style_c_coding_style", "label": "C++ Coding Style", "file_type": "document", "source_file": "I:\\GitHub\\Oferty_PV\\.kilo\\worktrees\\iced-dreadnought\\.agent\\rules\\cpp-coding-style.md", "source_location": "L12"}, {"id": "rules_cpp_coding_style_modern_c_c_17_20_23", "label": "Modern C++ (C++17/20/23)", "file_type": "document", "source_file": "I:\\GitHub\\Oferty_PV\\.kilo\\worktrees\\iced-dreadnought\\.agent\\rules\\cpp-coding-style.md", "source_location": "L16"}, {"id": "rules_cpp_coding_style_resource_management", "label": "Resource Management", "file_type": "document", "source_file": "I:\\GitHub\\Oferty_PV\\.kilo\\worktrees\\iced-dreadnought\\.agent\\rules\\cpp-coding-style.md", "source_location": "L23"}, {"id": "rules_cpp_coding_style_naming_conventions", "label": "Naming Conventions", "file_type": "document", "source_file": "I:\\GitHub\\Oferty_PV\\.kilo\\worktrees\\iced-dreadnought\\.agent\\rules\\cpp-coding-style.md", "source_location": "L30"}, {"id": "rules_cpp_coding_style_formatting", "label": "Formatting", "file_type": "document", "source_file": "I:\\GitHub\\Oferty_PV\\.kilo\\worktrees\\iced-dreadnought\\.agent\\rules\\cpp-coding-style.md", "source_location": "L38"}, {"id": "rules_cpp_coding_style_reference", "label": "Reference", "file_type": "document", "source_file": "I:\\GitHub\\Oferty_PV\\.kilo\\worktrees\\iced-dreadnought\\.agent\\rules\\cpp-coding-style.md", "source_location": "L43"}], "edges": [{"source": "i_github_oferty_pv_kilo_worktrees_iced_dreadnought_agent_rules_cpp_coding_style_md", "target": "rules_cpp_coding_style_c_coding_style", "relation": "contains", "confidence": "EXTRACTED", "source_file": "I:\\GitHub\\Oferty_PV\\.kilo\\worktrees\\iced-dreadnought\\.agent\\rules\\cpp-coding-style.md", "source_location": "L12", "weight": 1.0}, {"source": "rules_cpp_coding_style_c_coding_style", "target": "rules_cpp_coding_style_modern_c_c_17_20_23", "relation": "contains", "confidence": "EXTRACTED", "source_file": "I:\\GitHub\\Oferty_PV\\.kilo\\worktrees\\iced-dreadnought\\.agent\\rules\\cpp-coding-style.md", "source_location": "L16", "weight": 1.0}, {"source": "rules_cpp_coding_style_c_coding_style", "target": "rules_cpp_coding_style_resource_management", "relation": "contains", "confidence": "EXTRACTED", "source_file": "I:\\GitHub\\Oferty_PV\\.kilo\\worktrees\\iced-dreadnought\\.agent\\rules\\cpp-coding-style.md", "source_location": "L23", "weight": 1.0}, {"source": "rules_cpp_coding_style_c_coding_style", "target": "rules_cpp_coding_style_naming_conventions", "relation": "contains", "confidence": "EXTRACTED", "source_file": "I:\\GitHub\\Oferty_PV\\.kilo\\worktrees\\iced-dreadnought\\.agent\\rules\\cpp-coding-style.md", "source_location": "L30", "weight": 1.0}, {"source": "rules_cpp_coding_style_c_coding_style", "target": "rules_cpp_coding_style_formatting", "relation": "contains", "confidence": "EXTRACTED", "source_file": "I:\\GitHub\\Oferty_PV\\.kilo\\worktrees\\iced-dreadnought\\.agent\\rules\\cpp-coding-style.md", "source_location": "L38", "weight": 1.0}, {"source": "rules_cpp_coding_style_c_coding_style", "target": "rules_cpp_coding_style_reference", "relation": "contains", "confidence": "EXTRACTED", "source_file": "I:\\GitHub\\Oferty_PV\\.kilo\\worktrees\\iced-dreadnought\\.agent\\rules\\cpp-coding-style.md", "source_location": "L43", "weight": 1.0}], "input_tokens": 0, "output_tokens": 0}